README.md
pyproject.toml
setup.cfg
setup.py
print_sql_tool/__init__.py
print_sql_tool/print_sql_tool.py
print_sql_tool.egg-info/PKG-INFO
print_sql_tool.egg-info/SOURCES.txt
print_sql_tool.egg-info/dependency_links.txt
print_sql_tool.egg-info/requires.txt
print_sql_tool.egg-info/top_level.txt