Metadata-Version: 2.1
Name: print-sql-tool
Version: 0.0.4
Summary: print_sql_tool
Home-page: https://github.com/Rwwwrl/Django-sql-printer
Author: Alexey Sosov
Author-email: lesh.solowiew@yandex.ru
License: BSD-3-Clause
Classifier: Environment :: Web Environment
Classifier: Intended Audience :: Developers
Classifier: License :: OSI Approved :: BSD License
Classifier: Operating System :: OS Independent
Classifier: Programming Language :: Python :: 3.6
Classifier: Programming Language :: Python :: 3.7
Classifier: Programming Language :: Python :: 3.8
Classifier: Programming Language :: Python :: 3.9
Classifier: Programming Language :: Python :: 3.10
Requires-Python: >=3.6
